[
    {
        "textPayload": "Message received with ID [12345]: new message coming.",
        "timestamp": "2023-06-28T18:00:00Z"
    },
    {
        "textPayload": "Message acknowledged for ID [12345]: acknowledged message.",
        "timestamp": "2023-06-28T18:00:01Z"
    },
    {
        "textPayload": "Processing started for ID [12345]: start handle msg.",
        "timestamp": "2023-06-28T18:00:02Z"
    },
    {
        "textPayload": "Backend service called for ID [12345]: call backend service",
        "timestamp": "2023-06-28T18:00:03Z"
    },
    {
        "textPayload": "Message received with ID [67890]: new message coming.",
        "timestamp": "2023-06-28T18:00:10Z"
    },
    {
        "textPayload": "Message acknowledged for ID [67890]: acknowledged message.",
        "timestamp": "2023-06-28T18:00:11Z"
    },
    {
        "textPayload": "Processing started for ID [67890]: start handle msg.",
        "timestamp": "2023-06-28T18:00:12Z"
    },
    {
        "textPayload": "Backend service called for ID [67890]: call backend service",
        "timestamp": "2023-06-28T18:00:13Z"
    }
]
